{
  "users": [
    {
      "id": 2,
      "name": "Bret",
      "email": "Sincere@april.biz",
      "website": "hildegard.org"
    },
    {
      "id": 3,
      "name": "Bret",
      "email": "Sincere@april.biz",
      "website": "hildegard.org"
    },
    {
      "id": 4,
      "name": "Bret",
      "email": "Sincere@april.biz",
      "website": "hildegard.org"
    },
    {
      "id": 5,
      "name": "Bret",
      "email": "Sincere@april.biz",
      "website": "hildegard.org"
    },
    {
      "id": 6,
      "name": "Bret",
      "email": "Sincere@april.biz",
      "website": "hildegard.org"
    },
    {
      "id": 7,
      "name": "Bret",
      "email": "Sincere@april.biz",
      "website": "hildegard.org"
    },
    {
      "id": 8,
      "name": "Bret",
      "email": "Sincere@april.biz",
      "website": "hildegard.org"
    },
    {
      "id": 9,
      "name": "Bret",
      "email": "Sincere@april.biz",
      "website": "hildegard.org"
    },
    {
      "id": 10,
      "name": "Bret",
      "email": "Sincere@april.biz",
      "website": "hildegard.org"
    }
  ]
}